saccess_response/__init__.py
saccess_response/apps.py
saccess_response/exceptions.py
saccess_response/generics.py
saccess_response/mixins.py
saccess_response/pagination.py
saccess_response/response.py
saccess_response/views.py
saccess_response/viewsets.py
saccess_response/saccess_rest_framework_simplejwt/__init__.py
saccess_response/saccess_rest_framework_simplejwt/apps.py
saccess_response/saccess_rest_framework_simplejwt/views.py
django_saccess_response-1.0.4.dist-info/METADATA
django_saccess_response-1.0.4.dist-info/WHEEL
django_saccess_response-1.0.4.dist-info/top_level.txt
django_saccess_response-1.0.4.dist-info/RECORD
