Metadata-Version: 2.1
Name: django-saccess-response
Version: 1.0.4
Summary: Django app for customizing response
Home-page: https://github.com/QuvonchbekBobojonov/saccess_response
Author: Quvonchbek Bobojonov
Author-email: hi@moorfo.uz
Classifier: Development Status :: 3 - Alpha
Classifier: Intended Audience :: Developers
Classifier: License :: OSI Approved :: MIT License
Classifier: Programming Language :: Python :: 3
Classifier: Programming Language :: Python :: 3.6
Classifier: Programming Language :: Python :: 3.7
Classifier: Programming Language :: Python :: 3.8
Classifier: Programming Language :: Python :: 3.9
Classifier: Programming Language :: Python :: 3.10
Classifier: Programming Language :: Python :: 3.11
Classifier: Programming Language :: Python :: 3.12
Classifier: Programming Language :: Python :: 3.13
Classifier: Framework :: Django
Requires-Python: >=3.6
